space_translation_util/__init__.py
space_translation_util/__main__.py
space_translation_util-0.0.9.dist-info/METADATA
space_translation_util-0.0.9.dist-info/WHEEL
space_translation_util-0.0.9.dist-info/entry_points.txt
space_translation_util-0.0.9.dist-info/top_level.txt
space_translation_util-0.0.9.dist-info/RECORD
