Metadata-Version: 2.1
Name: space-translation-util
Version: 0.0.9
Summary: Space Translation Utility
Home-page: https://github.com/SpaceBank/space-translation-util
Author: Roman Akopov
Author-email: roman.akopovi@space.ge
License: UNKNOWN
Platform: UNKNOWN
Classifier: Development Status :: 4 - Beta
Classifier: Environment :: Console
Classifier: Intended Audience :: Developers
Classifier: License :: OSI Approved :: MIT License
Classifier: License :: Other/Proprietary License
Classifier: Operating System :: OS Independent
Classifier: Programming Language :: Python :: 3
Requires-Dist: colorama (>=0.4.1)
Requires-Dist: google-api-python-client (>=1.7.8)
Requires-Dist: google-auth-httplib2 (>=0.0.3)
Requires-Dist: google-auth-oauthlib (>=0.2.0)
